Metadata-Version: 2.4
Name: bach-snow_day_probability_api
Version: 1.0.0
Summary: RapidAPI: devify/snow-day-probability-api
Project-URL: Homepage, https://github.com/bachstudio/bach-snow_day_probability_api
Project-URL: Repository, https://github.com/bachstudio/bach-snow_day_probability_api
Project-URL: Documentation, https://github.com/bachstudio/bach-snow_day_probability_api#readme
Requires-Python: >=3.10
Requires-Dist: fastmcp>=2.0.0
Requires-Dist: httpx>=0.25.0
Provides-Extra: dev
Requires-Dist: black>=23.0.0; extra == 'dev'
Requires-Dist: pytest>=7.0.0; extra == 'dev'
